Metadata-Version: 2.1
Name: multiplespacolibrary
Version: 0.1.0
Summary: A library for checking multiples of 2 and 5.
Home-page: UNKNOWN
Author: pacobahena
Author-email: pakobahena72@gmail.com
License: UNKNOWN
Platform: UNKNOWN
Classifier: Programming Language :: Python :: 3
Classifier: License :: OSI Approved :: MIT License
Classifier: Operating System :: OS Independent
Requires-Python: >=3.9
License-File: LICENSE.txt
